{
  "events": [
    {
      "defined_class": "project.lincook.backend.security.JwtAuthenticationFilter",
      "event": "call",
      "id": 1,
      "lineno": 37,
      "method_id": "doFilterInternal",
      "parameters": [
        {
          "class": "org.springframework.security.web.header.HeaderWriterFilter$HeaderWriterRequest",
          "kind": "req",
          "name": "request",
          "object_id": 311795692,
          "value": "org.springframework.security.web.header.HeaderWriterFilter$HeaderWriterRequest@12959fec"
        },
        {
          "class": "org.springframework.security.web.header.HeaderWriterFilter$HeaderWriterResponse",
          "kind": "req",
          "name": "response",
          "object_id": 189034068,
          "value": "org.springframework.security.web.header.HeaderWriterFilter$HeaderWriterResponse@b446e54"
        },
        {
          "class": "org.springframework.security.web.FilterChainProxy$VirtualFilterChain",
          "kind": "req",
          "name": "filterChain",
          "object_id": 1288752746,
          "value": "org.springframework.security.web.FilterChainProxy$VirtualFilterChain@4cd0ce6a"
        }
      ],
      "path": "project/lincook/backend/security/JwtAuthenticationFilter.java",
      "receiver": {
        "class": "project.lincook.backend.security.JwtAuthenticationFilter",
        "object_id": 995760621,
        "value": "project.lincook.backend.security.JwtAuthenticationFilter@3b5a19ed"
      },
      "static": false,
      "thread_id": 51
    },
    {
      "defined_class": "project.lincook.backend.security.TokenProvider",
      "event": "call",
      "id": 2,
      "lineno": 47,
      "method_id": "validateAndGetUserId",
      "parameters": [
        {
          "class": "java.lang.String",
          "kind": "req",
          "name": "token",
          "object_id": 1265757667,
          "value": "eyJhbGciOiJIUzUxMiJ9.eyJzdWIiOiI0MSIsImlzcyI6IkxpbmNvb2siLCJhdWQiOiJVU0VSIiwiYXV0aCI6IlVTRVIiLCJpYXQiOjE2OTUzNjE1NzEsImV4cCI6MTY5NTQ0Nzk3MX0.PJhw_mnLVkX8D_o8Mi0rVadVXhhbPwnIi01SBnn-C9dPVhR3biK7pTrcVVBMNwn-CeLgRMzTtpuV20PhPYJ7Pw"
        }
      ],
      "path": "project/lincook/backend/security/TokenProvider.java",
      "receiver": {
        "class": "project.lincook.backend.security.TokenProvider",
        "object_id": 1402400433,
        "value": "project.lincook.backend.security.TokenProvider@5396eeb1"
      },
      "static": false,
      "thread_id": 51
    },
    {
      "elapsed": 0.00969354,
      "event": "return",
      "id": 3,
      "parent_id": 2,
      "return_value": {
        "class": "java.lang.String",
        "object_id": 1468954904,
        "value": "41"
      },
      "thread_id": 51
    },
    {
      "event": "call",
      "http_server_request": {
        "headers": {
          "authorization": "Bearer eyJhbGciOiJIUzUxMiJ9.eyJzdWIiOiI0MSIsImlzcyI6IkxpbmNvb2siLCJhdWQiOiJVU0VSIiwiYXV0aCI6IlVTRVIiLCJpYXQiOjE2OTUzNjE1NzEsImV4cCI6MTY5NTQ0Nzk3MX0.PJhw_mnLVkX8D_o8Mi0rVadVXhhbPwnIi01SBnn-C9dPVhR3biK7pTrcVVBMNwn-CeLgRMzTtpuV20PhPYJ7Pw",
          "content-length": "66",
          "postman-token": "1214a376-2bee-4a6b-9279-3a81d01c789b",
          "host": "localhost:8080",
          "content-type": "application/json",
          "connection": "keep-alive",
          "accept-encoding": "gzip, deflate, br",
          "user-agent": "PostmanRuntime/7.33.0",
          "accept": "*/*"
        },
        "normalized_path_info": "/auth/signin",
        "path_info": "/auth/signin",
        "protocol": "HTTP/1.1",
        "request_method": "POST"
      },
      "id": 4,
      "thread_id": 51
    },
    {
      "defined_class": "project.lincook.backend.controller.MemberController$SigninRequest",
      "event": "call",
      "id": 5,
      "lineno": 125,
      "method_id": "setEmail",
      "parameters": [
        {
          "class": "java.lang.String",
          "kind": "req",
          "name": "email",
          "object_id": 1907960681,
          "value": "hello14@world.com"
        }
      ],
      "path": "project/lincook/backend/controller/MemberController.java",
      "receiver": {
        "class": "project.lincook.backend.controller.MemberController$SigninRequest",
        "object_id": 1561950304,
        "value": "MemberController.SigninRequest(email=hello14@world.com, password=null, token=null)"
      },
      "static": false,
      "thread_id": 51
    },
    {
      "elapsed": 0.00029959,
      "event": "return",
      "id": 6,
      "parent_id": 5,
      "thread_id": 51
    },
    {
      "defined_class": "project.lincook.backend.controller.MemberController$SigninRequest",
      "event": "call",
      "id": 7,
      "lineno": 125,
      "method_id": "setPassword",
      "parameters": [
        {
          "class": "java.lang.String",
          "kind": "req",
          "name": "password",
          "object_id": 1380685417,
          "value": "12345"
        }
      ],
      "path": "project/lincook/backend/controller/MemberController.java",
      "receiver": {
        "class": "project.lincook.backend.controller.MemberController$SigninRequest",
        "object_id": 1561950304,
        "value": "MemberController.SigninRequest(email=hello14@world.com, password=12345, token=null)"
      },
      "static": false,
      "thread_id": 51
    },
    {
      "elapsed": 0,
      "event": "return",
      "id": 8,
      "parent_id": 7,
      "thread_id": 51
    },
    {
      "defined_class": "project.lincook.backend.controller.MemberController",
      "event": "call",
      "id": 9,
      "lineno": 83,
      "method_id": "authenticate",
      "parameters": [
        {
          "class": "project.lincook.backend.controller.MemberController$SigninRequest",
          "kind": "req",
          "name": "request",
          "object_id": 1561950304,
          "value": "MemberController.SigninRequest(email=hello14@world.com, password=12345, token=null)"
        }
      ],
      "path": "project/lincook/backend/controller/MemberController.java",
      "receiver": {
        "class": "project.lincook.backend.controller.MemberController",
        "object_id": 1242514050,
        "value": "project.lincook.backend.controller.MemberController@4a0f4282"
      },
      "static": false,
      "thread_id": 51
    },
    {
      "defined_class": "project.lincook.backend.service.MemberService",
      "event": "call",
      "id": 10,
      "lineno": 45,
      "method_id": "getByCredentials",
      "parameters": [
        {
          "class": "java.lang.String",
          "kind": "req",
          "name": "email",
          "object_id": 1907960681,
          "value": "hello14@world.com"
        },
        {
          "class": "java.lang.String",
          "kind": "req",
          "name": "password",
          "object_id": 1380685417,
          "value": "12345"
        },
        {
          "class": "org.springframework.security.crypto.bcrypt.BCryptPasswordEncoder",
          "kind": "req",
          "name": "encoder",
          "object_id": 443109552,
          "value": "org.springframework.security.crypto.bcrypt.BCryptPasswordEncoder@1a6950b0"
        }
      ],
      "path": "project/lincook/backend/service/MemberService.java",
      "receiver": {
        "class": "project.lincook.backend.service.MemberService",
        "object_id": 1546706639,
        "value": "project.lincook.backend.service.MemberService@5c30decf"
      },
      "static": false,
      "thread_id": 51
    },
    {
      "defined_class": "project.lincook.backend.repository.MemberRepository",
      "event": "call",
      "id": 11,
      "lineno": 28,
      "method_id": "findByUserEmail",
      "parameters": [
        {
          "class": "java.lang.String",
          "kind": "req",
          "name": "email",
          "object_id": 1907960681,
          "value": "hello14@world.com"
        }
      ],
      "path": "project/lincook/backend/repository/MemberRepository.java",
      "receiver": {
        "class": "project.lincook.backend.repository.MemberRepository",
        "object_id": 1413952420,
        "value": "project.lincook.backend.repository.MemberRepository@544733a4"
      },
      "static": false,
      "thread_id": 51
    },
    {
      "event": "call",
      "id": 12,
      "sql_query": {
        "database_type": "MySQL",
        "sql": "select member0_.member_id as member_i1_8_, member0_.address as address2_8_, member0_.auth_provider as auth_pro3_8_, member0_.email as email4_8_, member0_.gender as gender5_8_, member0_.latitude as latitude6_8_, member0_.longitude as longitud7_8_, member0_.name as name8_8_, member0_.password as password9_8_, member0_.role as role10_8_ from member member0_ where member0_.email=?"
      },
      "thread_id": 51
    },
    {
      "elapsed": 0,
      "event": "return",
      "id": 13,
      "parent_id": 12,
      "thread_id": 51
    },
    {
      "defined_class": "project.lincook.backend.entity.Gender",
      "event": "call",
      "id": 14,
      "lineno": 3,
      "method_id": "values",
      "path": "project/lincook/backend/entity/Gender.java",
      "static": true,
      "thread_id": 51
    },
    {
      "elapsed": 0,
      "event": "return",
      "id": 15,
      "parent_id": 14,
      "return_value": {
        "class": "[Lproject.lincook.backend.entity.Gender;",
        "object_id": 1320492032,
        "value": "[Lproject.lincook.backend.entity.Gender;@4eb51c00"
      },
      "thread_id": 51
    },
    {
      "elapsed": 0.0133747,
      "event": "return",
      "id": 16,
      "parent_id": 11,
      "return_value": {
        "class": "java.util.ArrayList",
        "object_id": 1391676835,
        "value": "[project.lincook.backend.entity.Member@427537c2]"
      },
      "thread_id": 51
    },
    {
      "elapsed": 0.02028584,
      "event": "return",
      "id": 17,
      "parent_id": 10,
      "return_value": {
        "class": "project.lincook.backend.entity.Member",
        "object_id": 1114978242,
        "value": "project.lincook.backend.entity.Member@427537c2"
      },
      "thread_id": 51
    },
    {
      "defined_class": "project.lincook.backend.security.TokenProvider",
      "event": "call",
      "id": 18,
      "lineno": 29,
      "method_id": "create",
      "parameters": [
        {
          "class": "project.lincook.backend.entity.Member",
          "kind": "req",
          "name": "memberEntity",
          "object_id": 1114978242,
          "value": "project.lincook.backend.entity.Member@427537c2"
        }
      ],
      "path": "project/lincook/backend/security/TokenProvider.java",
      "receiver": {
        "class": "project.lincook.backend.security.TokenProvider",
        "object_id": 1402400433,
        "value": "project.lincook.backend.security.TokenProvider@5396eeb1"
      },
      "static": false,
      "thread_id": 51
    },
    {
      "elapsed": 0.00220223,
      "event": "return",
      "id": 19,
      "parent_id": 18,
      "return_value": {
        "class": "java.lang.String",
        "object_id": 137456387,
        "value": "eyJhbGciOiJIUzUxMiJ9.eyJzdWIiOiI0MiIsImlzcyI6IkxpbmNvb2siLCJhdWQiOiJVU0VSIiwiYXV0aCI6IlVTRVIiLCJpYXQiOjE2OTUzNjg2NTYsImV4cCI6MTY5NTQ1NTA1Nn0.G6coaMO3y44baBy-MYNyLndUhuWeS9hhW0P6HulmOqEVyu0vGujvbUOhOONHzSB-dBRvQ719GksW73cXWMaDoQ"
      },
      "thread_id": 51
    },
    {
      "defined_class": "project.lincook.backend.dto.MemberDTO",
      "event": "call",
      "id": 20,
      "lineno": 12,
      "method_id": "builder",
      "path": "project/lincook/backend/dto/MemberDTO.java",
      "static": true,
      "thread_id": 51
    },
    {
      "elapsed": 0.00250005,
      "event": "return",
      "id": 21,
      "parent_id": 20,
      "return_value": {
        "class": "project.lincook.backend.dto.MemberDTO$MemberDTOBuilder",
        "object_id": 1916630683,
        "value": "MemberDTO.MemberDTOBuilder(token=null, email=null, password=null, name=null, role=null, gender=null, address=null, latitude=0.0, longitude=0.0)"
      },
      "thread_id": 51
    },
    {
      "defined_class": "project.lincook.backend.dto.MemberDTO$MemberDTOBuilder",
      "event": "call",
      "id": 22,
      "lineno": 12,
      "method_id": "email",
      "parameters": [
        {
          "class": "java.lang.String",
          "kind": "req",
          "name": "email",
          "object_id": 330136586,
          "value": "hello14@world.com"
        }
      ],
      "path": "project/lincook/backend/dto/MemberDTO.java",
      "receiver": {
        "class": "project.lincook.backend.dto.MemberDTO$MemberDTOBuilder",
        "object_id": 1916630683,
        "value": "MemberDTO.MemberDTOBuilder(token=null, email=hello14@world.com, password=null, name=null, role=null, gender=null, address=null, latitude=0.0, longitude=0.0)"
      },
      "static": false,
      "thread_id": 51
    },
    {
      "elapsed": 0.00069999,
      "event": "return",
      "id": 23,
      "parent_id": 22,
      "return_value": {
        "class": "project.lincook.backend.dto.MemberDTO$MemberDTOBuilder",
        "object_id": 1916630683,
        "value": "MemberDTO.MemberDTOBuilder(token=null, email=hello14@world.com, password=null, name=null, role=null, gender=null, address=null, latitude=0.0, longitude=0.0)"
      },
      "thread_id": 51
    },
    {
      "defined_class": "project.lincook.backend.dto.MemberDTO$MemberDTOBuilder",
      "event": "call",
      "id": 24,
      "lineno": 12,
      "method_id": "password",
      "parameters": [
        {
          "class": "java.lang.String",
          "kind": "req",
          "name": "password",
          "object_id": 1764247245,
          "value": "$2a$10$rPXeHd3TKKZLRn1jShBRKO0ahNFgth7eQpxrLN2HHoLogP42dpDfy"
        }
      ],
      "path": "project/lincook/backend/dto/MemberDTO.java",
      "receiver": {
        "class": "project.lincook.backend.dto.MemberDTO$MemberDTOBuilder",
        "object_id": 1916630683,
        "value": "MemberDTO.MemberDTOBuilder(token=null, email=hello14@world.com, password=$2a$10$rPXeHd3TKKZLRn1jShBRKO0ahNFgth7eQpxrLN2HHoLogP42dpDfy, name=null, role=null, gender=null, address=null, latitude=0.0, longitude=0.0)"
      },
      "static": false,
      "thread_id": 51
    },
    {
      "elapsed": 0,
      "event": "return",
      "id": 25,
      "parent_id": 24,
      "return_value": {
        "class": "project.lincook.backend.dto.MemberDTO$MemberDTOBuilder",
        "object_id": 1916630683,
        "value": "MemberDTO.MemberDTOBuilder(token=null, email=hello14@world.com, password=$2a$10$rPXeHd3TKKZLRn1jShBRKO0ahNFgth7eQpxrLN2HHoLogP42dpDfy, name=null, role=null, gender=null, address=null, latitude=0.0, longitude=0.0)"
      },
      "thread_id": 51
    },
    {
      "defined_class": "project.lincook.backend.dto.MemberDTO$MemberDTOBuilder",
      "event": "call",
      "id": 26,
      "lineno": 12,
      "method_id": "role",
      "parameters": [
        {
          "class": "java.lang.String",
          "kind": "req",
          "name": "role",
          "object_id": 1010308179,
          "value": "ROLE_USER"
        }
      ],
      "path": "project/lincook/backend/dto/MemberDTO.java",
      "receiver": {
        "class": "project.lincook.backend.dto.MemberDTO$MemberDTOBuilder",
        "object_id": 1916630683,
        "value": "MemberDTO.MemberDTOBuilder(token=null, email=hello14@world.com, password=$2a$10$rPXeHd3TKKZLRn1jShBRKO0ahNFgth7eQpxrLN2HHoLogP42dpDfy, name=null, role=ROLE_USER, gender=null, address=null, latitude=0.0, longitude=0.0)"
      },
      "static": false,
      "thread_id": 51
    },
    {
      "elapsed": 0,
      "event": "return",
      "id": 27,
      "parent_id": 26,
      "return_value": {
        "class": "project.lincook.backend.dto.MemberDTO$MemberDTOBuilder",
        "object_id": 1916630683,
        "value": "MemberDTO.MemberDTOBuilder(token=null, email=hello14@world.com, password=$2a$10$rPXeHd3TKKZLRn1jShBRKO0ahNFgth7eQpxrLN2HHoLogP42dpDfy, name=null, role=ROLE_USER, gender=null, address=null, latitude=0.0, longitude=0.0)"
      },
      "thread_id": 51
    },
    {
      "defined_class": "project.lincook.backend.dto.MemberDTO$MemberDTOBuilder",
      "event": "call",
      "id": 28,
      "lineno": 12,
      "method_id": "token",
      "parameters": [
        {
          "class": "java.lang.String",
          "kind": "req",
          "name": "token",
          "object_id": 137456387,
          "value": "eyJhbGciOiJIUzUxMiJ9.eyJzdWIiOiI0MiIsImlzcyI6IkxpbmNvb2siLCJhdWQiOiJVU0VSIiwiYXV0aCI6IlVTRVIiLCJpYXQiOjE2OTUzNjg2NTYsImV4cCI6MTY5NTQ1NTA1Nn0.G6coaMO3y44baBy-MYNyLndUhuWeS9hhW0P6HulmOqEVyu0vGujvbUOhOONHzSB-dBRvQ719GksW73cXWMaDoQ"
        }
      ],
      "path": "project/lincook/backend/dto/MemberDTO.java",
      "receiver": {
        "class": "project.lincook.backend.dto.MemberDTO$MemberDTOBuilder",
        "object_id": 1916630683,
        "value": "MemberDTO.MemberDTOBuilder(token=eyJhbGciOiJIUzUxMiJ9.eyJzdWIiOiI0MiIsImlzcyI6IkxpbmNvb2siLCJhdWQiOiJVU0VSIiwiYXV0aCI6IlVTRVIiLCJpYXQiOjE2OTUzNjg2NTYsImV4cCI6MTY5NTQ1NTA1Nn0.G6coaMO3y44baBy-MYNyLndUhuWeS9hhW0P6HulmOqEVyu0vGujvbUOhOONHzSB-dBRvQ719GksW73cXWMaDoQ, email=hello14@world.com, password=$2a$10$rPXeHd3TKKZLRn1jShBRKO0ahNFgth7eQpxrLN2HHoLogP42dpDfy, name=null, role=ROLE_USER, gender=null, address=null, latitude=0.0, longitude=0.0)"
      },
      "static": false,
      "thread_id": 51
    },
    {
      "elapsed": 0,
      "event": "return",
      "id": 29,
      "parent_id": 28,
      "return_value": {
        "class": "project.lincook.backend.dto.MemberDTO$MemberDTOBuilder",
        "object_id": 1916630683,
        "value": "MemberDTO.MemberDTOBuilder(token=eyJhbGciOiJIUzUxMiJ9.eyJzdWIiOiI0MiIsImlzcyI6IkxpbmNvb2siLCJhdWQiOiJVU0VSIiwiYXV0aCI6IlVTRVIiLCJpYXQiOjE2OTUzNjg2NTYsImV4cCI6MTY5NTQ1NTA1Nn0.G6coaMO3y44baBy-MYNyLndUhuWeS9hhW0P6HulmOqEVyu0vGujvbUOhOONHzSB-dBRvQ719GksW73cXWMaDoQ, email=hello14@world.com, password=$2a$10$rPXeHd3TKKZLRn1jShBRKO0ahNFgth7eQpxrLN2HHoLogP42dpDfy, name=null, role=ROLE_USER, gender=null, address=null, latitude=0.0, longitude=0.0)"
      },
      "thread_id": 51
    },
    {
      "defined_class": "project.lincook.backend.dto.MemberDTO$MemberDTOBuilder",
      "event": "call",
      "id": 30,
      "lineno": 12,
      "method_id": "build",
      "path": "project/lincook/backend/dto/MemberDTO.java",
      "receiver": {
        "class": "project.lincook.backend.dto.MemberDTO$MemberDTOBuilder",
        "object_id": 1916630683,
        "value": "MemberDTO.MemberDTOBuilder(token=eyJhbGciOiJIUzUxMiJ9.eyJzdWIiOiI0MiIsImlzcyI6IkxpbmNvb2siLCJhdWQiOiJVU0VSIiwiYXV0aCI6IlVTRVIiLCJpYXQiOjE2OTUzNjg2NTYsImV4cCI6MTY5NTQ1NTA1Nn0.G6coaMO3y44baBy-MYNyLndUhuWeS9hhW0P6HulmOqEVyu0vGujvbUOhOONHzSB-dBRvQ719GksW73cXWMaDoQ, email=hello14@world.com, password=$2a$10$rPXeHd3TKKZLRn1jShBRKO0ahNFgth7eQpxrLN2HHoLogP42dpDfy, name=null, role=ROLE_USER, gender=null, address=null, latitude=0.0, longitude=0.0)"
      },
      "static": false,
      "thread_id": 51
    },
    {
      "elapsed": 0,
      "event": "return",
      "id": 31,
      "parent_id": 30,
      "return_value": {
        "class": "project.lincook.backend.dto.MemberDTO",
        "object_id": 1572542963,
        "value": "MemberDTO(token=eyJhbGciOiJIUzUxMiJ9.eyJzdWIiOiI0MiIsImlzcyI6IkxpbmNvb2siLCJhdWQiOiJVU0VSIiwiYXV0aCI6IlVTRVIiLCJpYXQiOjE2OTUzNjg2NTYsImV4cCI6MTY5NTQ1NTA1Nn0.G6coaMO3y44baBy-MYNyLndUhuWeS9hhW0P6HulmOqEVyu0vGujvbUOhOONHzSB-dBRvQ719GksW73cXWMaDoQ, email=hello14@world.com, password=$2a$10$rPXeHd3TKKZLRn1jShBRKO0ahNFgth7eQpxrLN2HHoLogP42dpDfy, name=null, role=ROLE_USER, gender=null, address=null, latitude=0.0, longitude=0.0)"
      },
      "thread_id": 51
    },
    {
      "elapsed": 0.03531693,
      "event": "return",
      "id": 32,
      "parent_id": 9,
      "return_value": {
        "class": "org.springframework.http.ResponseEntity",
        "object_id": 998391800,
        "value": "<200 OK OK,MemberDTO(token=eyJhbGciOiJIUzUxMiJ9.eyJzdWIiOiI0MiIsImlzcyI6IkxpbmNvb2siLCJhdWQiOiJVU0VSIiwiYXV0aCI6IlVTRVIiLCJpYXQiOjE2OTUzNjg2NTYsImV4cCI6MTY5NTQ1NTA1Nn0.G6coaMO3y44baBy-MYNyLndUhuWeS9hhW0P6HulmOqEVyu0vGujvbUOhOONHzSB-dBRvQ719GksW73cXWMaDoQ, email=hello14@world.com, password=$2a$10$rPXeHd3TKKZLRn1jShBRKO0ahNFgth7eQpxrLN2HHoLogP42dpDfy, name=null, role=ROLE_USER, gender=null, address=null, latitude=0.0, longitude=0.0),[]>"
      },
      "thread_id": 51
    },
    {
      "elapsed": 0.05437175,
      "event": "return",
      "http_server_response": {
        "headers": {
          "X-Frame-Options": "SAMEORIGIN",
          "Transfer-Encoding": "chunked",
          "Keep-Alive": "timeout=60",
          "Cache-Control": "no-cache, no-store, max-age=0, must-revalidate",
          "X-Content-Type-Options": "nosniff",
          "Connection": "keep-alive",
          "Pragma": "no-cache",
          "Expires": "0",
          "X-XSS-Protection": "1; mode=block",
          "Date": "Fri, 22 Sep 2023 07:44:17 GMT",
          "Content-Type": "application/json"
        },
        "status": 200
      },
      "id": 33,
      "parent_id": 4,
      "thread_id": 51
    },
    {
      "elapsed": 0.06535655,
      "event": "return",
      "id": 34,
      "parent_id": 1,
      "thread_id": 51
    }
  ],
  "version": "1.2",
  "metadata": {
    "name": "POST /auth/signin (200) - 16:44:16.317",
    "app": "backend",
    "language": {
      "name": "java",
      "version": "17.0.8+7-LTS",
      "engine": "OpenJDK 64-Bit Server VM"
    },
    "client": {
      "name": "appmap-java",
      "url": "https://github.com/appland/appmap-java"
    },
    "recorder": {
      "name": "request_recording",
      "type": "request"
    },
    "recording": {},
    "framework": {}
  },
  "classMap": [
    {
      "children": [
        {
          "children": [
            {
              "children": [
                {
                  "children": [
                    {
                      "children": [
                        {
                          "name": "email",
                          "type": "function",
                          "static": false,
                          "location": "project/lincook/backend/dto/MemberDTO.java:12"
                        },
                        {
                          "name": "build",
                          "type": "function",
                          "static": false,
                          "location": "project/lincook/backend/dto/MemberDTO.java:12"
                        },
                        {
                          "name": "password",
                          "type": "function",
                          "static": false,
                          "location": "project/lincook/backend/dto/MemberDTO.java:12"
                        },
                        {
                          "name": "role",
                          "type": "function",
                          "static": false,
                          "location": "project/lincook/backend/dto/MemberDTO.java:12"
                        },
                        {
                          "name": "token",
                          "type": "function",
                          "static": false,
                          "location": "project/lincook/backend/dto/MemberDTO.java:12"
                        }
                      ],
                      "name": "MemberDTO$MemberDTOBuilder",
                      "type": "class"
                    },
                    {
                      "children": [
                        {
                          "name": "builder",
                          "type": "function",
                          "static": true,
                          "location": "project/lincook/backend/dto/MemberDTO.java:12"
                        }
                      ],
                      "name": "MemberDTO",
                      "type": "class"
                    }
                  ],
                  "name": "dto",
                  "type": "package"
                },
                {
                  "children": [
                    {
                      "children": [
                        {
                          "name": "validateAndGetUserId",
                          "type": "function",
                          "static": false,
                          "location": "project/lincook/backend/security/TokenProvider.java:47"
                        },
                        {
                          "name": "create",
                          "type": "function",
                          "static": false,
                          "location": "project/lincook/backend/security/TokenProvider.java:29"
                        }
                      ],
                      "name": "TokenProvider",
                      "type": "class"
                    },
                    {
                      "children": [
                        {
                          "name": "doFilterInternal",
                          "type": "function",
                          "static": false,
                          "location": "project/lincook/backend/security/JwtAuthenticationFilter.java:37"
                        }
                      ],
                      "name": "JwtAuthenticationFilter",
                      "type": "class"
                    }
                  ],
                  "name": "security",
                  "type": "package"
                },
                {
                  "children": [
                    {
                      "children": [
                        {
                          "name": "findByUserEmail",
                          "type": "function",
                          "static": false,
                          "location": "project/lincook/backend/repository/MemberRepository.java:28"
                        }
                      ],
                      "name": "MemberRepository",
                      "type": "class"
                    }
                  ],
                  "name": "repository",
                  "type": "package"
                },
                {
                  "children": [
                    {
                      "children": [
                        {
                          "name": "setPassword",
                          "type": "function",
                          "static": false,
                          "location": "project/lincook/backend/controller/MemberController.java:125"
                        },
                        {
                          "name": "setEmail",
                          "type": "function",
                          "static": false,
                          "location": "project/lincook/backend/controller/MemberController.java:125"
                        }
                      ],
                      "name": "MemberController$SigninRequest",
                      "type": "class"
                    },
                    {
                      "children": [
                        {
                          "name": "authenticate",
                          "type": "function",
                          "static": false,
                          "location": "project/lincook/backend/controller/MemberController.java:83"
                        }
                      ],
                      "name": "MemberController",
                      "type": "class"
                    }
                  ],
                  "name": "controller",
                  "type": "package"
                },
                {
                  "children": [
                    {
                      "children": [
                        {
                          "name": "values",
                          "type": "function",
                          "static": true,
                          "location": "project/lincook/backend/entity/Gender.java:3"
                        }
                      ],
                      "name": "Gender",
                      "type": "class"
                    }
                  ],
                  "name": "entity",
                  "type": "package"
                },
                {
                  "children": [
                    {
                      "children": [
                        {
                          "name": "getByCredentials",
                          "type": "function",
                          "static": false,
                          "location": "project/lincook/backend/service/MemberService.java:45"
                        }
                      ],
                      "name": "MemberService",
                      "type": "class"
                    }
                  ],
                  "name": "service",
                  "type": "package"
                }
              ],
              "name": "backend",
              "type": "package"
            }
          ],
          "name": "lincook",
          "type": "package"
        }
      ],
      "name": "project",
      "type": "package"
    },
    {
      "type": "http",
      "name": "HTTP server requests",
      "children": [
        {
          "type": "route",
          "name": "POST /auth/signin"
        }
      ]
    },
    {
      "type": "database",
      "name": "Database",
      "children": [
        {
          "type": "query",
          "name": "select member0_.member_id as member_i1_8_, member0_.address as address2_8_, member0_.auth_provider as auth_pro3_8_, member0_.email as email4_8_, member0_.gender as gender5_8_, member0_.latitude as latitude6_8_, member0_.longitude as longitud7_8_, member0_.name as name8_8_, member0_.password as password9_8_, member0_.role as role10_8_ from member member0_ where member0_.email=?"
        }
      ]
    }
  ]
}